wsidicomizer/__init__.py
wsidicomizer/cli.py
wsidicomizer/config.py
wsidicomizer/dicomizer_source.py
wsidicomizer/image_data.py
wsidicomizer/metadata.py
wsidicomizer/wsidicomizer.py
wsidicomizer/extras/bioformats/__init__.py
wsidicomizer/extras/bioformats/bioformats_image_data.py
wsidicomizer/extras/bioformats/bioformats_reader.py
wsidicomizer/extras/bioformats/bioformats_source.py
wsidicomizer/extras/isyntax/__init__.py
wsidicomizer/extras/isyntax/isyntax_image_data.py
wsidicomizer/extras/isyntax/isyntax_metadata.py
wsidicomizer/extras/isyntax/isyntax_source.py
wsidicomizer/extras/openslide/__init__.py
wsidicomizer/extras/openslide/openslide.py
wsidicomizer/extras/openslide/openslide_image_data.py
wsidicomizer/extras/openslide/openslide_source.py
wsidicomizer/sources/__init__.py
wsidicomizer/sources/czi/__init__.py
wsidicomizer/sources/czi/czi_image_data.py
wsidicomizer/sources/czi/czi_metadata.py
wsidicomizer/sources/czi/czi_source.py
wsidicomizer/sources/openslide_like/__init__.py
wsidicomizer/sources/openslide_like/openslide_like_image_data.py
wsidicomizer/sources/openslide_like/openslide_like_metadata.py
wsidicomizer/sources/openslide_like/openslide_like_source.py
wsidicomizer/sources/opentile/__init__.py
wsidicomizer/sources/opentile/opentile_image_data.py
wsidicomizer/sources/opentile/opentile_metadata.py
wsidicomizer/sources/opentile/opentile_source.py
wsidicomizer/sources/tiffslide/__init__.py
wsidicomizer/sources/tiffslide/tiffslide_image_data.py
wsidicomizer/sources/tiffslide/tiffslide_source.py
wsidicomizer-0.24.0.dist-info/METADATA
wsidicomizer-0.24.0.dist-info/WHEEL
wsidicomizer-0.24.0.dist-info/entry_points.txt
wsidicomizer-0.24.0.dist-info/licenses/LICENCE
wsidicomizer-0.24.0.dist-info/RECORD
