Metadata-Version: 2.4
Name: wsidicomizer
Version: 0.24.0
Summary: Tool for reading WSI files from proprietary formats and optionally convert them to to DICOM
Project-URL: Repository, https://github.com/imi-bigpicture/wsidicomizer
Author-email: Erik O Gabrielsson <erik.o.gabrielsson@sectra.com>
License: Apache-2.0
License-File: LICENCE
Keywords: converter,dicom,digital pathology,whole slide image
Classifier: Development Status :: 4 - Beta
Classifier: Intended Audience :: Developers
Classifier: Intended Audience :: Healthcare Industry
Classifier: Intended Audience :: Science/Research
Classifier: Operating System :: OS Independent
Classifier: Topic :: Scientific/Engineering :: Medical Science Apps.
Requires-Python: >=3.10
Requires-Dist: click<9.0.0,>=8.3.0
Requires-Dist: czifile<2020.0.0,>=2019.7.2
Requires-Dist: imagecodecs<2025.0.0,>=2024.12.30
Requires-Dist: numpy>=1.22.0
Requires-Dist: opentile<0.20.0,>=0.19.0
Requires-Dist: pydicom>=3.0.0
Requires-Dist: tiffslide<3.0.0,>=2.5.1
Requires-Dist: wsidicom<0.30.0,>=0.29.0
Provides-Extra: bioformats
Requires-Dist: ome-types<0.6.0,>=0.5.0; extra == 'bioformats'
Requires-Dist: scyjava<2.0.0,>=1.8.1; extra == 'bioformats'
Provides-Extra: isyntax
Requires-Dist: pyisyntax<0.2.0,>=0.1.2; extra == 'isyntax'
Provides-Extra: openslide
Requires-Dist: openslide-python<2.0.0,>=1.3.0; extra == 'openslide'
